combinational circuits using gate modeling/optimized_adder.v/optimized_adder.v
module optimized_adder(input a,b,cin,output sum,carry);
wire w1,w2,w3;
xor x1(w1,a,b);
xor x2(sum,w1,cin);
and a1(w2,a,b);
and a2(w3,w1,cin);
or o1(carry,w2,w3);
endmodule

combinational circuits using gate modeling/optimized_adder.v/optimized_adder_tb.v
module optimized_adder_tb;
reg a,b,cin;
wire sum,carry;

optimized_adder dut(.a(a),.b(b),.cin(cin),.sum(sum),.carry(carry));

initial begin
$dumpfile("optimized_adder.vcd");
$dumpvars(0,optimized_adder_tb);
$monitor("time=%0t, a=%b , b=%b, cin=%b | sum=%b, carry=%b",$time,a,b,cin,sum,carry);

a=0;b=0;cin=0;#10;
a=0;b=0;cin=1;#10;
a=0;b=1;cin=0;#10;
a=0;b=1;cin=1;#10;
a=1;b=0;cin=0;#10;
a=1;b=0;cin=1;#10;
a=1;b=1;cin=0;#10;
a=1;b=1;cin=1;#10;

$finish;
end
endmodule

combinational circuits using gate modeling/optimized_adder.v/optimized_adder.vcd
$date
	Thu Mar 26 09:28:42 2026
$end
$version
	Icarus Verilog
$end
$timescale
	1s
$end
$scope module optimized_adder_tb $end
$var wire 1 ! sum $end
$var wire 1 " carry $end
$var reg 1 # a $end
$var reg 1 $ b $end
$var reg 1 % cin $end
$scope module dut $end
$var wire 1 # a $end
$var wire 1 $ b $end
$var wire 1 " carry $end
$var wire 1 % cin $end
$var wire 1 ! sum $end
$var wire 1 & w1 $end
$var wire 1 ' w2 $end
$var wire 1 ( w3 $end
$upscope $end
$upscope $end
$enddefinitions $end
$comment Show the parameter values. $end
$dumpall
$end
#0
$dumpvars
0(
0'
0&
0%
0$
0#
0"
0!
$end
#10
1!
1%
#20
1&
0%
1$
#30
1"
0!
1(
1%
#40
0"
1!
0(
0%
0$
1#
#50
1"
0!
1(
1%
#60
0(
0&
1'
0%
1$
#70
1!
1%
