sequential_ckt_using_behavioral_modeling/d_flipflop_syn_reset_en/d_flipflop_syn_reset_en.v
module d_flipflop_sync_en(input d,input rst,input clk,input en,output reg q);

always @(posedge clk)begin
   
     if(rst)
          
         q<=1'b0;
     else if(en)
         q<=d;
      else

         q<=q;
 end
 endmodule

sequential_ckt_using_behavioral_modeling/d_flipflop_syn_reset_en/d_flipflop_syn_reset_en_tb.v
module d_flipflop_sync_en_tb;

reg d;
reg rst;
reg clk;
reg en;
wire q;

d_flipflop_sync_en dut (.d(d),.rst(rst),.clk(clk),.en(en),.q(q));
 
always #5 clk= ~clk;  
 
initial begin 

    $dumpfile("d_flipflop_sync_en.vcd");
    $dumpvars(0,d_flipflop_sync_en_tb);

    $monitor("time=%0t | d=%b,rst=%b,clk=%b,en=%b | q=%b",$time,d,rst,clk,en,q);
      clk=0;
      rst=1;
      d=0;
      en=0;
  
     
      #12 rst=0;
      #8 en=1;
      #9 d=1;
      #12 d=0;
      #18 d=1;
      #4 en=0;
     
     $finish;

$finish;
end

endmodule

sequential_ckt_using_behavioral_modeling/d_flipflop_syn_reset_en/d_flipflop_sync_en.vcd
$date
	Wed Apr  1 13:41:12 2026
$end
$version
	Icarus Verilog
$end
$timescale
	1s
$end
$scope module d_flipflop_sync_en_tb $end
$var wire 1 ! q $end
$var reg 1 " clk $end
$var reg 1 # d $end
$var reg 1 $ en $end
$var reg 1 % rst $end
$scope module dut $end
$var wire 1 " clk $end
$var wire 1 # d $end
$var wire 1 $ en $end
$var wire 1 % rst $end
$var reg 1 ! q $end
$upscope $end
$upscope $end
$enddefinitions $end
$comment Show the parameter values. $end
$dumpall
$end
#0
$dumpvars
1%
0$
0#
0"
x!
$end
#5
0!
1"
#10
0"
#12
0%
#15
1"
#20
0"
1$
#25
1"
#29
1#
#30
0"
#35
1!
1"
#40
0"
#41
0#
#45
0!
1"
#50
0"
#55
1"
#59
1#
#60
0"
#63
0$
