combinational ckt using gate modeling/optimized_subtractor.v/optimized_subtractor.v
module optimized_subtractor(input a,b,bin,output diff,borrow);

wire w1,w2,w3,w4,w5;
xor x1(w1,a,b);
xor x2(diff,w1,bin);
and a1(w2,w4,b);
and a2(w3,w5,bin);
not n1(w4,a);
not n2(w5,w1);
or o1(borrow,w3,w2);

endmodule

combinational ckt using gate modeling/optimized_subtractor.v/optimized_subtractor_tb.v
module optimized_subtractor_tb;

reg a,b,bin;
wire diff,borrow;

optimized_subtractor dut(.a(a),.b(b),.bin(bin),.diff(diff),.borrow(borrow));

initial begin

$dumpfile("optimized_subtractor.vcd");
$dumpvars(0,optimized_subtractor_tb);

$monitor("time=%0t | a=%b,b=%b,bin=%b| diff=%b,borrow=%b",$time,a,b,bin,diff,borrow);

a=0;b=0;bin=0;#10;
a=0;b=0;bin=1;#10;
a=0;b=1;bin=0;#10;
a=0;b=1;bin=1;#10;
a=1;b=0;bin=0;#10;
a=1;b=0;bin=1;#10;
a=1;b=1;bin=0;#10;
a=1;b=1;bin=1;#10;

$finish;
end
endmodule

combinational ckt using gate modeling/optimized_subtractor.v/optimized_subtractor.vcd
$date
	Thu Mar 26 09:55:38 2026
$end
$version
	Icarus Verilog
$end
$timescale
	1s
$end
$scope module optimized_subtractor_tb $end
$var wire 1 ! diff $end
$var wire 1 " borrow $end
$var reg 1 # a $end
$var reg 1 $ b $end
$var reg 1 % bin $end
$scope module dut $end
$var wire 1 # a $end
$var wire 1 $ b $end
$var wire 1 % bin $end
$var wire 1 " borrow $end
$var wire 1 ! diff $end
$var wire 1 & w1 $end
$var wire 1 ' w2 $end
$var wire 1 ( w3 $end
$var wire 1 ) w4 $end
$var wire 1 * w5 $end
$upscope $end
$upscope $end
$enddefinitions $end
$comment Show the parameter values. $end
$dumpall
$end
#0
$dumpvars
1*
1)
0(
0'
0&
0%
0$
0#
0"
0!
$end
#10
1"
1!
1(
1%
#20
0*
0(
1&
1'
0%
1$
#30
0!
1%
#40
0"
1!
0'
0)
0%
0$
1#
#50
0!
1%
#60
1*
0&
0%
1$
#70
1"
1!
1(
1%
