sequential_ckt_using_behavioral_modeling/piso_shift_register/piso_shift_register.v
module piso_shift_register(input [3:0] din,input rst_n,input clk,input load,output dout);
 
reg [3:0]q;
 
always @(posedge clk or negedge rst_n)begin
   
     if(!rst_n)
          
         q<=4'b0000;
     else if (load)

         q<=din;
     else
         q<=q<<1;
        
 end
        
  assign dout= q[3];   

 endmodule

sequential_ckt_using_behavioral_modeling/piso_shift_register/piso_shift_register_tb.v
module piso_shift_register_tb;

reg [3:0]din;
reg rst_n;
reg clk;
reg load;
wire dout;
piso_shift_register dut (.din(din),.rst_n(rst_n),.clk(clk),.load(load),.dout(dout));
 
always #5 clk= ~clk;  


initial begin 

    $dumpfile("piso_shift_register.vcd");
    $dumpvars(0,piso_shift_register_tb);

    $monitor("time=%0t | din=%b,rst_n=%b,clk=%b,load=%b | dout=%b",$time,din,rst_n,clk,load,dout);
      clk=0;
      rst_n=0;
      din=4'b0000;
      load=1;
      #3 din=4'b1010;

    #3 rst_n=1;
    #16 load=0;

        
    
 #50 $finish;
 end

endmodule

sequential_ckt_using_behavioral_modeling/piso_shift_register/piso_shift_register.vcd
$date
	Thu Apr  2 13:15:33 2026
$end
$version
	Icarus Verilog
$end
$timescale
	1s
$end
$scope module piso_shift_register_tb $end
$var wire 1 ! dout $end
$var reg 1 " clk $end
$var reg 4 # din [3:0] $end
$var reg 1 $ load $end
$var reg 1 % rst_n $end
$scope module dut $end
$var wire 1 " clk $end
$var wire 4 & din [3:0] $end
$var wire 1 $ load $end
$var wire 1 % rst_n $end
$var wire 1 ! dout $end
$var reg 4 ' q [3:0] $end
$upscope $end
$upscope $end
$enddefinitions $end
$comment Show the parameter values. $end
$dumpall
$end
#0
$dumpvars
b0 '
b0 &
0%
1$
b0 #
0"
0!
$end
#3
b1010 #
b1010 &
#5
1"
#6
1%
#10
0"
#15
1!
b1010 '
1"
#20
0"
#22
0$
#25
0!
b100 '
1"
#30
0"
#35
1!
b1000 '
1"
#40
0"
#45
0!
b0 '
1"
