sequential_ckt_using_behavioral_modeling/pipo_shift_register/pipo_shift_register.v
module pipo_shift_register(input [3:0] din,input rst_n,input clk,input load,output [3:0]dout);
 
reg [3:0]q;
 
always @(posedge clk or negedge rst_n)begin
   
     if(!rst_n)
          
         q<=4'b0000;
     else if (load)

         q<=din;
     else 
         q<=q;
        
 end 

 assign dout = q;

 endmodule

sequential_ckt_using_behavioral_modeling/pipo_shift_register/pipo_shift_register_tb.v
module pipo_shift_register_tb;

reg [3:0]din;
reg rst_n;
reg clk;
reg load;
wire [3:0]dout;
pipo_shift_register dut (.din(din),.rst_n(rst_n),.clk(clk),.load(load),.dout(dout));
 
always #5 clk= ~clk;  

integer i;
initial begin 

    $dumpfile("pipo_shift_register.vcd");
    $dumpvars(0,pipo_shift_register_tb);

    $monitor("time=%0t | din=%b,rst_n=%b,clk=%b,load=%b | dout=%b",$time,din,rst_n,clk,load,dout);
      clk=0;
      rst_n=0;
      load=0;
      din=4'b0000;


    #10 rst_n=1;
    
 for(i=0;i<16;i=i+1)begin
    
    din=i;
    load=1;#10;
    load=0;
    #10;
end
  $finish;
end

endmodule

sequential_ckt_using_behavioral_modeling/pipo_shift_register/pipo_shift_register.vcd
$date
	Thu Apr  2 14:29:01 2026
$end
$version
	Icarus Verilog
$end
$timescale
	1s
$end
$scope module pipo_shift_register_tb $end
$var wire 4 ! dout [3:0] $end
$var reg 1 " clk $end
$var reg 4 # din [3:0] $end
$var reg 1 $ load $end
$var reg 1 % rst_n $end
$var integer 32 & i [31:0] $end
$scope module dut $end
$var wire 1 " clk $end
$var wire 4 ' din [3:0] $end
$var wire 4 ( dout [3:0] $end
$var wire 1 $ load $end
$var wire 1 % rst_n $end
$var reg 4 ) q [3:0] $end
$upscope $end
$upscope $end
$enddefinitions $end
$comment Show the parameter values. $end
$dumpall
$end
#0
$dumpvars
b0 )
b0 (
b0 '
bx &
0%
0$
b0 #
0"
b0 !
$end
#5
1"
#10
0"
1$
b0 &
1%
#15
1"
#20
0"
0$
#25
1"
#30
0"
1$
b1 #
b1 '
b1 &
#35
b1 !
b1 (
b1 )
1"
#40
0"
0$
#45
1"
#50
0"
1$
b10 #
b10 '
b10 &
#55
b10 !
b10 (
b10 )
1"
#60
0"
0$
#65
1"
#70
0"
1$
b11 #
b11 '
b11 &
#75
b11 !
b11 (
b11 )
1"
#80
0"
0$
#85
1"
#90
0"
1$
b100 #
b100 '
b100 &
#95
b100 !
b100 (
b100 )
1"
#100
0"
0$
#105
1"
#110
0"
1$
b101 #
b101 '
b101 &
#115
b101 !
b101 (
b101 )
1"
#120
0"
0$
#125
1"
#130
0"
1$
b110 #
b110 '
b110 &
#135
b110 !
b110 (
b110 )
1"
#140
0"
0$
#145
1"
#150
0"
1$
b111 #
b111 '
b111 &
#155
b111 !
b111 (
b111 )
1"
#160
0"
0$
#165
1"
#170
0"
1$
b1000 #
b1000 '
b1000 &
#175
b1000 !
b1000 (
b1000 )
1"
#180
0"
0$
#185
1"
#190
0"
1$
b1001 #
b1001 '
b1001 &
#195
b1001 !
b1001 (
b1001 )
1"
#200
0"
0$
#205
1"
#210
0"
1$
b1010 #
b1010 '
b1010 &
#215
b1010 !
b1010 (
b1010 )
1"
#220
0"
0$
#225
1"
#230
0"
1$
b1011 #
b1011 '
b1011 &
#235
b1011 !
b1011 (
b1011 )
1"
#240
0"
0$
#245
1"
#250
0"
1$
b1100 #
b1100 '
b1100 &
#255
b1100 !
b1100 (
b1100 )
1"
#260
0"
0$
#265
1"
#270
0"
1$
b1101 #
b1101 '
b1101 &
#275
b1101 !
b1101 (
b1101 )
1"
#280
0"
0$
#285
1"
#290
0"
1$
b1110 #
b1110 '
b1110 &
#295
b1110 !
b1110 (
b1110 )
1"
#300
0"
0$
#305
1"
#310
0"
1$
b1111 #
b1111 '
b1111 &
#315
b1111 !
b1111 (
b1111 )
1"
#320
0"
0$
#325
1"
#330
0"
b10000 &
