verilog_test_1/fsm_10110_more_overlap/fsm_10110_more_overlap.v
module fsm_10110_detector(input d,input rst_n,clk,output detect);

localparam s0=3'd0,s1=3'd1,s2=3'd2,s3=3'd3,s4=3'd4,s5=3'd5;

reg [2:0] state,next_state;

always @(posedge clk or negedge rst_n)begin

    if(!rst_n)

        state <= s0;
    else

        state <= next_state;

end

always @(*)begin

    if(state == s0)begin

        if(d == 1)

            next_state = s1;
        else

            next_state = s0;
    end

    else if (state == s1)begin

        if(d == 0)

            next_state = s2;

        else

            next_state = s1;

    end

    else if(state == s2)begin

        if(d == 1)

        next_state = s3;

    else 

        next_state = s0;

end

    else if(state == s3)begin

        if(d == 1)

        next_state = s4;

    else 

        next_state = s0;

end

    else if(state == s4)begin

        if(d == 0)

        next_state = s5;

    else 

        next_state = s1;
end

    else if(state == s5)begin

        if(d == 1)

        next_state = s3;

    else 

        next_state = s0;

end
end

assign detect = (state == s5)  ? 1'b1 : 1'b0;


endmodule

verilog_test_1/fsm_10110_more_overlap/fsm_10110_more_overlap_tb.v
module fsm_10110_detector_tb;

reg d;
reg rst_n,clk;

wire detect;

fsm_10110_detector dut (.d(d),.rst_n(rst_n),.clk(clk),.detect(detect));

always #5 clk = ~clk;

initial begin

    $dumpfile("fsm_10110_detector.vcd");
    $dumpvars(0,fsm_10110_detector_tb);

    $monitor("time =%0t | d=%b,rst_n=%b,clk=%b | detect=%b ",$time,d,rst_n,clk,detect);

end

initial begin

    clk =0;
    d=0;
    rst_n=0;

    @(posedge clk);
    rst_n=1;

    d=1;
    @(posedge clk);

    d=0;
    @(posedge clk);

     d=1;
    @(posedge clk);

     d=1;
    @(posedge clk);

     d=0;
    @(posedge clk);

     d=1;
    @(posedge clk);

     d=1;
    @(posedge clk);

     d=0;
    @(posedge clk);





    

    $finish;

end

endmodule

verilog_test_1/fsm_10110_more_overlap/fsm_10110_detector.vcd
$date
	Fri Apr 10 13:02:50 2026
$end
$version
	Icarus Verilog
$end
$timescale
	1s
$end
$scope module fsm_10110_detector_tb $end
$var wire 1 ! detect $end
$var reg 1 " clk $end
$var reg 1 # d $end
$var reg 1 $ rst_n $end
$scope module dut $end
$var wire 1 " clk $end
$var wire 1 # d $end
$var wire 1 $ rst_n $end
$var wire 1 ! detect $end
$var parameter 3 % s0 $end
$var parameter 3 & s1 $end
$var parameter 3 ' s2 $end
$var parameter 3 ( s3 $end
$var parameter 3 ) s4 $end
$var parameter 3 * s5 $end
$var reg 3 + next_state [2:0] $end
$var reg 3 , state [2:0] $end
$upscope $end
$upscope $end
$enddefinitions $end
$comment Show the parameter values. $end
$dumpall
b101 *
b100 )
b11 (
b10 '
b1 &
b0 %
$end
#0
$dumpvars
b0 ,
b0 +
0$
0#
0"
0!
$end
#5
b1 +
1#
1$
1"
#10
0"
#15
b1 ,
b10 +
0#
1"
#20
0"
#25
b10 ,
b11 +
1#
1"
#30
0"
#35
b100 +
b11 ,
1"
#40
0"
#45
b100 ,
b101 +
0#
1"
#50
0"
#55
1!
b101 ,
b11 +
1#
1"
#60
0"
#65
b100 +
0!
b11 ,
1"
#70
0"
#75
b100 ,
b101 +
0#
1"
#80
0"
#85
b0 +
1!
b101 ,
1"
