combinational_ckt_using_dataflow_&_behavioral_modeling/comparator_4bit.v/comparator_4bit.v
module comparator_4bit_dataflow (input  [3:0] a,input  [3:0] b,output gt,output lt,output eq);

assign eq = (a == b);   
assign gt = (a >  b);   
assign lt = (a <  b);   

endmodule


module comparator_4bit_behavioral (input  [3:0] a,input  [3:0] b,output reg gt,output reg lt,output reg eq);

always @(*) begin
    if (a == b) begin
        eq = 1'b1;
        gt = 1'b0;
        lt = 1'b0;
    end
    else if (a > b) begin
        gt = 1'b1;
        eq = 1'b0;
        lt = 1'b0;
    end
    else begin
        lt = 1'b1;
        gt = 1'b0;
        eq = 1'b0;
    end
end

endmodule

 module comparator_4bit_top (input  [3:0] a,input  [3:0] b,output gt_da,output lt_da,output eq_da,output gt_be,output lt_be,output eq_be);

 comparator_4bit_dataflow c1(.a(a),.b(b),.gt(gt_da),.lt(lt_da),.eq(eq_da));
comparator_4bit_behavioral c2(.a(a),.b(b),.gt(gt_be),.lt(lt_be),.eq(eq_be));

endmodule

combinational_ckt_using_dataflow_&_behavioral_modeling/comparator_4bit.v/comparator_4bit_tb.v
module comparator_4bit_tb;

    reg  [3:0] a;
    reg  [3:0] b;

    wire gt_da,lt_da,eq_da;
     wire gt_be,lt_be,eq_be;

 comparator_4bit_top dut (.a(a),.b(b),.gt_da(gt_da),.lt_da(lt_da),.eq_da(eq_da),.gt_be(gt_be),.lt_be(lt_be),.eq_be(eq_be));

    integer i;

    initial begin
   $dumpfile("comparator_4bit.vcd");
   $dumpvars(0,comparator_4bit_tb);

        $monitor("time=%0t | a=%b b=%b |  gt_da=%b lt_da=%b eq_da=%b | gt_be=%b lt_be=%b eq_be=%b",
                 $time, a, b, gt_da, lt_da, eq_da, gt_be, lt_be, eq_be);

    for(i=0;i<16;i=i+1)begin
     
      {a,b}=i;#10;

    end
$finish;
end

endmodule

combinational_ckt_using_dataflow_&_behavioral_modeling/comparator_4bit.v/comparator_4bit.vcd
$date
	Tue Mar 31 14:56:37 2026
$end
$version
	Icarus Verilog
$end
$timescale
	1s
$end
$scope module comparator_4bit_tb $end
$var wire 1 ! lt_da $end
$var wire 1 " lt_be $end
$var wire 1 # gt_da $end
$var wire 1 $ gt_be $end
$var wire 1 % eq_da $end
$var wire 1 & eq_be $end
$var reg 4 ' a [3:0] $end
$var reg 4 ( b [3:0] $end
$var integer 32 ) i [31:0] $end
$scope module dut $end
$var wire 4 * a [3:0] $end
$var wire 4 + b [3:0] $end
$var wire 1 ! lt_da $end
$var wire 1 " lt_be $end
$var wire 1 # gt_da $end
$var wire 1 $ gt_be $end
$var wire 1 % eq_da $end
$var wire 1 & eq_be $end
$scope module c1 $end
$var wire 4 , a [3:0] $end
$var wire 4 - b [3:0] $end
$var wire 1 ! lt $end
$var wire 1 # gt $end
$var wire 1 % eq $end
$upscope $end
$scope module c2 $end
$var wire 4 . a [3:0] $end
$var wire 4 / b [3:0] $end
$var reg 1 & eq $end
$var reg 1 $ gt $end
$var reg 1 " lt $end
$upscope $end
$upscope $end
$upscope $end
$enddefinitions $end
$comment Show the parameter values. $end
$dumpall
$end
#0
$dumpvars
b0 /
b0 .
b0 -
b0 ,
b0 +
b0 *
b0 )
b0 (
b0 '
1&
1%
0$
0#
0"
0!
$end
#10
0&
1"
0%
1!
b1 (
b1 +
b1 -
b1 /
b1 )
#20
b10 (
b10 +
b10 -
b10 /
b10 )
#30
b11 (
b11 +
b11 -
b11 /
b11 )
#40
b100 (
b100 +
b100 -
b100 /
b100 )
#50
b101 (
b101 +
b101 -
b101 /
b101 )
#60
b110 (
b110 +
b110 -
b110 /
b110 )
#70
b111 (
b111 +
b111 -
b111 /
b111 )
#80
b1000 (
b1000 +
b1000 -
b1000 /
b1000 )
#90
b1001 (
b1001 +
b1001 -
b1001 /
b1001 )
#100
b1010 (
b1010 +
b1010 -
b1010 /
b1010 )
#110
b1011 (
b1011 +
b1011 -
b1011 /
b1011 )
#120
b1100 (
b1100 +
b1100 -
b1100 /
b1100 )
#130
b1101 (
b1101 +
b1101 -
b1101 /
b1101 )
#140
b1110 (
b1110 +
b1110 -
b1110 /
b1110 )
#150
b1111 (
b1111 +
b1111 -
b1111 /
b1111 )
#160
b10000 )
