combinational_ckt_using_dataflow_&_behavioral_modeling/parity_generator_checker.v/parity_generator_checker.v
module parity_generator_dataflow(input [3:0]data,output parity);

assign parity=^data;

endmodule

module parity_generator_behavioral(input [3:0]data,output reg parity);

always @(*)begin

 parity=^data;

 end

endmodule

module parity_checker_dataflow(input [3:0]data,input parity,output error);

assign error=^{data,parity};

endmodule

module parity_checker_behavioral(input [3:0]data,input parity,output reg error);

always @(*)begin

 error=^{data,parity};

 end

 endmodule


 module parity_generator_checker_top(input [3:0]data,output parity_da,output parity_be,output error_da,output error_be);

 wire w1,w2;

 parity_generator_dataflow g2(.data(data),.parity(w1));
 parity_generator_behavioral g1(.data(data),.parity(w2));

parity_checker_dataflow c1(.data(data),.parity(w1),.error(error_da));
parity_checker_behavioral c2(.data(data),.parity(w2),.error(error_be));

assign parity_da=w1;
assign parity_be=w2;

endmodule

combinational_ckt_using_dataflow_&_behavioral_modeling/parity_generator_checker.v/parity_generator_checker_tb.v
module parity_generator_checker_tb;

reg [3:0]data;
wire parity_da;
wire parity_be;
wire error_da;
wire error_be;

parity_generator_checker_top dut(.data(data),.parity_da(parity_da),.parity_be(parity_be),.error_da(error_da),.error_be(error_be));

integer i;

initial begin 
    $dumpfile("parity_generator_checker.vcd");
    $dumpvars(0,parity_generator_checker_tb);

    $monitor("time=%0t | data=%b | parity_da=%b,parity_be=%b,error_da=%b,error_be=%b",$time,data,parity_da,parity_be,error_da,error_be);

    for(i=0;i<16;i=i+1)begin

        data=i;#10;

    end

$finish;

end
endmodule

combinational_circuits_using_dataflow_and_behavioral_modeling/parity_generator_checker.v/parity_generator_checker.vcd
$date
	Wed Apr  1 07:38:25 2026
$end
$version
	Icarus Verilog
$end
$timescale
	1s
$end
$scope module parity_generator_checker_tb $end
$var wire 1 ! parity_da $end
$var wire 1 " parity_be $end
$var wire 1 # error_da $end
$var wire 1 $ error_be $end
$var reg 4 % data [3:0] $end
$var integer 32 & i [31:0] $end
$scope module dut $end
$var wire 4 ' data [3:0] $end
$var wire 1 " parity_be $end
$var wire 1 ! parity_da $end
$var wire 1 ( w2 $end
$var wire 1 ) w1 $end
$var wire 1 # error_da $end
$var wire 1 $ error_be $end
$scope module c1 $end
$var wire 4 * data [3:0] $end
$var wire 1 ) parity $end
$var wire 1 # error $end
$upscope $end
$scope module c2 $end
$var wire 4 + data [3:0] $end
$var wire 1 ( parity $end
$var reg 1 $ error $end
$upscope $end
$scope module g1 $end
$var wire 4 , data [3:0] $end
$var reg 1 ( parity $end
$upscope $end
$scope module g2 $end
$var wire 4 - data [3:0] $end
$var wire 1 ) parity $end
$upscope $end
$upscope $end
$upscope $end
$enddefinitions $end
$comment Show the parameter values. $end
$dumpall
$end
#0
$dumpvars
b0 -
b0 ,
b0 +
b0 *
0)
0(
b0 '
b0 &
b0 %
0$
0#
0"
0!
$end
#10
1"
1(
0#
1!
1)
b1 %
b1 '
b1 *
b1 +
b1 ,
b1 -
b1 &
#20
b10 %
b10 '
b10 *
b10 +
b10 ,
b10 -
b10 &
#30
0"
0(
0#
0!
0)
b11 %
b11 '
b11 *
b11 +
b11 ,
b11 -
b11 &
#40
1"
1(
0#
1!
1)
b100 %
b100 '
b100 *
b100 +
b100 ,
b100 -
b100 &
#50
0"
0(
0#
0!
0)
b101 %
b101 '
b101 *
b101 +
b101 ,
b101 -
b101 &
#60
b110 %
b110 '
b110 *
b110 +
b110 ,
b110 -
b110 &
#70
1"
1(
0#
1!
1)
b111 %
b111 '
b111 *
b111 +
b111 ,
b111 -
b111 &
#80
b1000 %
b1000 '
b1000 *
b1000 +
b1000 ,
b1000 -
b1000 &
#90
0"
0(
0#
0!
0)
b1001 %
b1001 '
b1001 *
b1001 +
b1001 ,
b1001 -
b1001 &
#100
b1010 %
b1010 '
b1010 *
b1010 +
b1010 ,
b1010 -
b1010 &
#110
1"
1(
0#
1!
1)
b1011 %
b1011 '
b1011 *
b1011 +
b1011 ,
b1011 -
b1011 &
#120
0"
0(
0#
0!
0)
b1100 %
b1100 '
b1100 *
b1100 +
b1100 ,
b1100 -
b1100 &
#130
1"
1(
0#
1!
1)
b1101 %
b1101 '
b1101 *
b1101 +
b1101 ,
b1101 -
b1101 &
#140
b1110 %
b1110 '
b1110 *
b1110 +
b1110 ,
b1110 -
b1110 &
#150
0"
0(
0#
0!
0)
b1111 %
b1111 '
b1111 *
b1111 +
b1111 ,
b1111 -
b1111 &
#160
b10000 &
