sequential_ckt_using_behavioral_modeling/fsm_1010_detector_moore_non_overlap/fsm_1010_detector.v
module fsm_seq_detector(input din,input rst_n,input clk,output reg detect);

localparam s0=3'd0,s1=3'd1,s2=3'd2,s3=3'd3,s4=3'd4;

reg [2:0] state,next_state;

always @(posedge clk or negedge rst_n)begin

    if (!rst_n)

        state<=s0;
    else 

        state<=next_state;
end

always @(*)begin

    if(state == s0)begin

        if (din==1)

            next_state=s1;
        else 
            next_state=s0;
    end

   
    else if(state == s1)begin

        if (din==0)

            next_state=s2;
        else 
            next_state=s1;
    end

     else if(state == s2)begin

        if (din==1)

            next_state=s3;
        else 
            next_state=s0;

    end

     else if(state == s3)begin

        if (din==0)

            next_state=s4;
        else 
            next_state=s1;

    end

     else if(state == s4)begin

        if (din==1)

            next_state=s1;
        else 
            next_state=s0;

    end

end

always @(*)begin

      if(state == s4)

         detect = 1;

        else 
           
         detect = 0;   

end

endmodule

sequential_ckt_using_behavioral_modeling/fsm_1010_detector_moore_non_overlap/fsm_1010_detector_tb.v
module fsm_seq_detector_tb;

reg din;
reg rst_n;
reg clk;

wire detect;

fsm_seq_detector dut (.din(din),.rst_n(rst_n),.clk(clk),.detect(detect));

always #5 clk = ~clk;

initial begin

    $dumpfile("fsm_seq_detector.vcd");
    $dumpvars(0,fsm_seq_detector_tb);

    $monitor("time=%0t | din=%b,rst_n=%b,clk=%b | detect=%b ", $time,din,rst_n,clk,detect);

    clk=0;
    rst_n=0;
    din=0;

    @(posedge clk);
    rst_n=1;

    din=1;
    @(posedge clk);

    din=0;
    @(posedge clk);

    
    din=1;
    @(posedge clk);

     
    din=0;
    @(posedge clk);

    
    din=1;
    @(posedge clk);

    
    din=0;
    @(posedge clk);


$finish;

end
endmodule

sequential_ckt_using_behavioral_modeling/fsm_1010_detector_moore_non_overlap/fsm_seq_detector.vcd
$date
	Mon Apr  6 09:19:13 2026
$end
$version
	Icarus Verilog
$end
$timescale
	1s
$end
$scope module fsm_seq_detector_tb $end
$var wire 1 ! detect $end
$var reg 1 " clk $end
$var reg 1 # din $end
$var reg 1 $ rst_n $end
$scope module dut $end
$var wire 1 " clk $end
$var wire 1 # din $end
$var wire 1 $ rst_n $end
$var parameter 3 % s0 $end
$var parameter 3 & s1 $end
$var parameter 3 ' s2 $end
$var parameter 3 ( s3 $end
$var parameter 3 ) s4 $end
$var reg 1 ! detect $end
$var reg 3 * next_state [2:0] $end
$var reg 3 + state [2:0] $end
$upscope $end
$upscope $end
$enddefinitions $end
$comment Show the parameter values. $end
$dumpall
b100 )
b11 (
b10 '
b1 &
b0 %
$end
#0
$dumpvars
b0 +
b0 *
0$
0#
0"
0!
$end
#5
b1 *
1#
1$
1"
#10
0"
#15
b1 +
b10 *
0#
1"
#20
0"
#25
b10 +
b11 *
1#
1"
#30
0"
#35
b11 +
b100 *
0#
1"
#40
0"
#45
1!
b100 +
b1 *
1#
1"
#50
0"
#55
0!
b1 +
b10 *
0#
1"
#60
0"
#65
b0 *
b10 +
1"
