verilog_assignments/programmable_counter/programmable_counter.v
module programmable_counter#(parameter width = 4)(input load,input [width-1:0]load_val,input en,input [width-1:0]max_val,input rst_n,clk,output [width-1:0]count,output done);

reg[width-1:0]q;

always @(posedge clk or negedge rst_n)begin

    if (!rst_n)begin

        q <= 4'b0;

    end

        else if (load)begin

            q <= load_val;

    end
        
    else if (en)begin

        if(q == max_val)

            q <= 0;

        else 

            q <= q + 1;

    end

        else begin

            q <= q;

        end
    end

    assign count = q;
    assign done = (q == max_val) ? 1'b1 : 1'b0;

    endmodule

verilog_assignments/programmable_counter/programmable_counter_tb.v
module programmable_counter_tb;

reg load;
reg [3:0]load_val;
reg en;
reg [3:0]max_val;
reg rst_n,clk;

wire [3:0]count;
wire done;

programmable_counter  #(.width(4)) dut(.load(load),.load_val(load_val),.en(en),.max_val(max_val),.rst_n(rst_n),.clk(clk),.count(count),.done(done));

always #5 clk = ~clk;

initial begin 

    $dumpfile("programmable_counter.vcd");
    $dumpvars(0,programmable_counter_tb);

    $monitor("time=%0t | load=%b,load_val=%b,max_val=%b,en=%b,rst_n=%b,clk=%b | count =%b,done=%b",$time,load,load_val,max_val,en,rst_n,clk,count,done);

end

initial begin

    clk =0;
    rst_n=0;
    load_val=4'b0;
    max_val=4'b0;
    en=0;
    load=0;

    @(posedge clk);
    rst_n=1;

    load=1;
    load_val = 4'b1;
    @(posedge clk);
    load=0;

    en=1;
    max_val=4'b1111;
    @(posedge clk);
    

    repeat(16)@(posedge clk);
    en=0;

    $finish;

end

endmodule

verilog_assignments/programmable_counter/programmable_counter.vcd
$date
	Sun Apr 12 11:00:02 2026
$end
$version
	Icarus Verilog
$end
$timescale
	1s
$end
$scope module programmable_counter_tb $end
$var wire 1 ! done $end
$var wire 4 " count [3:0] $end
$var reg 1 # clk $end
$var reg 1 $ en $end
$var reg 1 % load $end
$var reg 4 & load_val [3:0] $end
$var reg 4 ' max_val [3:0] $end
$var reg 1 ( rst_n $end
$scope module dut $end
$var wire 1 # clk $end
$var wire 4 ) count [3:0] $end
$var wire 1 $ en $end
$var wire 1 % load $end
$var wire 4 * load_val [3:0] $end
$var wire 4 + max_val [3:0] $end
$var wire 1 ( rst_n $end
$var wire 1 ! done $end
$var parameter 32 , width $end
$var reg 4 - q [3:0] $end
$upscope $end
$upscope $end
$enddefinitions $end
$comment Show the parameter values. $end
$dumpall
b100 ,
$end
#0
$dumpvars
b0 -
b0 +
b0 *
b0 )
0(
b0 '
b0 &
0%
0$
0#
b0 "
1!
$end
#5
0!
b1 "
b1 )
b1 -
b1 &
b1 *
1%
1(
1#
#10
0#
#15
b10 "
b10 )
b10 -
b1111 '
b1111 +
1$
0%
1#
#20
0#
#25
b11 "
b11 )
b11 -
1#
#30
0#
#35
b100 "
b100 )
b100 -
1#
#40
0#
#45
b101 "
b101 )
b101 -
1#
#50
0#
#55
b110 "
b110 )
b110 -
1#
#60
0#
#65
b111 "
b111 )
b111 -
1#
#70
0#
#75
b1000 "
b1000 )
b1000 -
1#
#80
0#
#85
b1001 "
b1001 )
b1001 -
1#
#90
0#
#95
b1010 "
b1010 )
b1010 -
1#
#100
0#
#105
b1011 "
b1011 )
b1011 -
1#
#110
0#
#115
b1100 "
b1100 )
b1100 -
1#
#120
0#
#125
b1101 "
b1101 )
b1101 -
1#
#130
0#
#135
b1110 "
b1110 )
b1110 -
1#
#140
0#
#145
1!
b1111 "
b1111 )
b1111 -
1#
#150
0#
#155
0!
b0 "
b0 )
b0 -
1#
#160
0#
#165
b1 "
b1 )
b1 -
1#
#170
0#
#175
b10 "
b10 )
b10 -
1#
#180
0#
#185
0$
1#
