sequential_ckt_using_behavioral_modeling/register_4bit/register_4bit.v
module register_4bit(input [3:0]d,input rst_n,input clk,input en,output reg [3:0]q);

always @(posedge clk or negedge rst_n)begin
   
     if(!rst_n)
          
         q<=4'b0000;
     else if (en)

         q<=d;
        
     else 
        
        q <=q;   

 end
 endmodule

sequential_ckt_using_behavioral_modeling/register_4bit/register_4bit_tb.v
module register_4bit_tb;

reg [3:0]d;
reg rst_n;
reg clk;
reg en;
wire [3:0]q;
register_4bit dut (.d(d),.rst_n(rst_n),.clk(clk),.en(en),.q(q));
 
always #5 clk= ~clk;  

integer i;
initial begin 

    $dumpfile("register_4bit.vcd");
    $dumpvars(0,register_4bit_tb);

    $monitor("time=%0t | d=%b,rst_n=%b,clk=%b,en=%b | q=%b",$time,d,rst_n,clk,en,q);
      clk=0;
      rst_n=0;
      en=0;
      d=4'b0000;
  
       

     @(posedge clk);
     rst_n=1;
     en=1;

 for(i=0;i<16;i=i+1)begin
    
    d=i;
    @(posedge clk);
     
end
  $finish;
end

endmodule

sequential_ckt_using_behavioral_modeling/register_4bit/register_4bit.vcd
$date
	Thu Apr  2 08:55:59 2026
$end
$version
	Icarus Verilog
$end
$timescale
	1s
$end
$scope module register_4bit_tb $end
$var wire 4 ! q [3:0] $end
$var reg 1 " clk $end
$var reg 4 # d [3:0] $end
$var reg 1 $ en $end
$var reg 1 % rst_n $end
$var integer 32 & i [31:0] $end
$scope module dut $end
$var wire 1 " clk $end
$var wire 4 ' d [3:0] $end
$var wire 1 $ en $end
$var wire 1 % rst_n $end
$var reg 4 ( q [3:0] $end
$upscope $end
$upscope $end
$enddefinitions $end
$comment Show the parameter values. $end
$dumpall
$end
#0
$dumpvars
b0 (
b0 '
bx &
0%
0$
b0 #
0"
b0 !
$end
#5
1"
#6
1$
#10
0"
#15
1"
#18
b0 &
1%
#20
0"
#24
b1 #
b1 '
b1 &
#25
b1 !
b1 (
1"
#30
0"
b10 #
b10 '
b10 &
#35
b10 !
b10 (
1"
#36
b11 #
b11 '
b11 &
#40
0"
#42
b100 #
b100 '
b100 &
#45
b100 !
b100 (
1"
#48
b101 #
b101 '
b101 &
#50
0"
#54
b110 #
b110 '
b110 &
#55
b110 !
b110 (
1"
#60
0"
b111 #
b111 '
b111 &
#65
b111 !
b111 (
1"
#66
b1000 #
b1000 '
b1000 &
#70
0"
#72
b1001 #
b1001 '
b1001 &
#75
b1001 !
b1001 (
1"
#78
b1010 #
b1010 '
b1010 &
#80
0"
#84
b1011 #
b1011 '
b1011 &
#85
b1011 !
b1011 (
1"
#90
0"
b1100 #
b1100 '
b1100 &
#95
b1100 !
b1100 (
1"
#96
b1101 #
b1101 '
b1101 &
#100
0"
#102
b1110 #
b1110 '
b1110 &
#105
b1110 !
b1110 (
1"
#108
b1111 #
b1111 '
b1111 &
#110
0"
#114
b10000 &
