verilog_assignments/Axi_lite_fsm/Axi_lite_fsm.v
module axi_lite_fsm (
    input  wire clk,
    input  wire rst_n,

    input  wire start_write,

    output reg  awvalid,
    output reg  wvalid,
    output reg  bready,

    input  wire awready,
    input  wire wready,
    input  wire bvalid
);

    localparam IDLE       = 2'd0,
               WRITE_ADDR = 2'd1,
               WRITE_DATA = 2'd2,
               WRITE_RESP = 2'd3;

    reg [1:0] state, next_state;

    // STATE REGISTER
    always @(posedge clk or negedge rst_n) begin
        if (!rst_n)
            state <= IDLE;
        else
            state <= next_state;
    end

    // NEXT STATE LOGIC
    always @(*) begin
        next_state = state;
        case (state)
            IDLE:
                if (start_write)
                    next_state = WRITE_ADDR;

            WRITE_ADDR:
                if (awready)
                    next_state = WRITE_DATA;

            WRITE_DATA:
                if (wready)
                    next_state = WRITE_RESP;

            WRITE_RESP:
                if (bvalid)
                    next_state = IDLE;
        endcase
    end

    // OUTPUT LOGIC (CORRECT AXI STYLE)
    always @(posedge clk or negedge rst_n) begin
        if (!rst_n) begin
            awvalid <= 0;
            wvalid  <= 0;
            bready  <= 0;
        end else begin
            awvalid <= (state == WRITE_ADDR);
            wvalid  <= (state == WRITE_DATA);
            bready  <= (state == WRITE_RESP);
        end
    end

endmodule

verilog_assignments/Axi_lite_fsm/Axi_lite_fsm_tb.v
module axi_lite_fsm_tb;

    reg clk;
    reg rst_n;
    reg start_write;

    wire awvalid;
    reg  awready;

    wire wvalid;
    reg  wready;

    reg  bvalid;
    wire bready;

    // DUT
    axi_lite_fsm dut (
        .clk(clk),
        .rst_n(rst_n),
        .start_write(start_write),
        .awvalid(awvalid),
        .awready(awready),
        .wvalid(wvalid),
        .wready(wready),
        .bvalid(bvalid),
        .bready(bready)
    );

    // CLOCK
    always #5 clk = ~clk;

    initial begin
        $dumpfile("axi_lite_fsm.vcd");
        $dumpvars(0, axi_lite_fsm_tb);

        $monitor("t=%0t | awv=%b awr=%b | wv=%b wr=%b | bv=%b br=%b",
                 $time, awvalid, awready, wvalid, wready, bvalid, bready);
    end

    initial begin
        // INIT
        clk = 0;
        rst_n = 0;
        start_write = 0;
        awready = 0;
        wready  = 0;
        bvalid  = 0;

        // RESET
        #20 rst_n = 1;

        // START WRITE
        @(posedge clk);
        start_write = 1;
        @(posedge clk);
        start_write = 0;

        // ADDRESS HANDSHAKE
        repeat (2) @(posedge clk);
        awready = 1;
        @(posedge clk);
        awready = 0;

        // DATA HANDSHAKE
        repeat (2) @(posedge clk);
        wready = 1;
        @(posedge clk);
        wready = 0;

        // RESPONSE HANDSHAKE
        repeat (2) @(posedge clk);
        bvalid = 1;
        @(posedge clk);
        bvalid = 0;

        repeat (5) @(posedge clk);
        $finish;
    end

endmodule

verilog_assignments/Axi_lite_fsm/axi_lite_fsm.vcd
$date
	Tue May 19 06:26:03 2026
$end
$version
	Icarus Verilog
$end
$timescale
	1s
$end
$scope module axi_lite_fsm_tb $end
$var wire 1 ! wvalid $end
$var wire 1 " bready $end
$var wire 1 # awvalid $end
$var reg 1 $ awready $end
$var reg 1 % bvalid $end
$var reg 1 & clk $end
$var reg 1 ' rst_n $end
$var reg 1 ( start_write $end
$var reg 1 ) wready $end
$scope module dut $end
$var wire 1 $ awready $end
$var wire 1 % bvalid $end
$var wire 1 & clk $end
$var wire 1 ' rst_n $end
$var wire 1 ( start_write $end
$var wire 1 ) wready $end
$var parameter 2 * IDLE $end
$var parameter 2 + WRITE_ADDR $end
$var parameter 2 , WRITE_DATA $end
$var parameter 2 - WRITE_RESP $end
$var reg 1 # awvalid $end
$var reg 1 " bready $end
$var reg 2 . next_state [1:0] $end
$var reg 2 / state [1:0] $end
$var reg 1 ! wvalid $end
$upscope $end
$upscope $end
$enddefinitions $end
$comment Show the parameter values. $end
$dumpall
b11 -
b10 ,
b1 +
b0 *
$end
#0
$dumpvars
b0 /
b0 .
0)
0(
0'
0&
0%
0$
0#
0"
0!
$end
#5
1&
#10
0&
#15
1&
#20
0&
1'
#25
b1 .
1(
1&
#30
0&
#35
b1 /
b1 .
0(
1&
#40
0&
#45
1#
1&
#50
0&
#55
b10 .
1$
1&
#60
0&
#65
b10 /
b10 .
0$
1&
#70
0&
#75
1!
0#
1&
#80
0&
#85
b11 .
1)
1&
#90
0&
#95
b11 /
b11 .
0)
1&
#100
0&
#105
1"
0!
1&
#110
0&
#115
b0 .
1%
1&
#120
0&
#125
b0 /
b0 .
0%
1&
#130
0&
#135
0"
1&
