combinational_ckt_using_dataflow_&_behavioral_modeling/4to16_decoder_data_beh.v/4to16_decoder_data_beh.v
module decoder_4to16_dataflow (input [3:0] a,output [15:0]d);

    assign d[0]  = ~a[3] & ~a[2] & ~a[1] & ~a[0];
    assign d[1]  = ~a[3] & ~a[2] & ~a[1] &  a[0];
    assign d[2]  = ~a[3] & ~a[2] &  a[1] & ~a[0];
    assign d[3]  = ~a[3] & ~a[2] &  a[1] &  a[0];

    assign d[4]  = ~a[3] &  a[2] & ~a[1] & ~a[0];
    assign d[5]  = ~a[3] &  a[2] & ~a[1] &  a[0];
    assign d[6]  = ~a[3] &  a[2] &  a[1] & ~a[0];
    assign d[7]  = ~a[3] &  a[2] &  a[1] &  a[0];

    assign d[8]  =  a[3] & ~a[2] & ~a[1] & ~a[0];
    assign d[9]  =  a[3] & ~a[2] & ~a[1] &  a[0];
    assign d[10] =  a[3] & ~a[2] &  a[1] & ~a[0];
    assign d[11] =  a[3] & ~a[2] &  a[1] &  a[0];

    assign d[12] =  a[3] &  a[2] & ~a[1] & ~a[0];
    assign d[13] =  a[3] &  a[2] & ~a[1] &  a[0];
    assign d[14] =  a[3] &  a[2] &  a[1] & ~a[0];
    assign d[15] =  a[3] &  a[2] &  a[1] &  a[0];

endmodule

module decoder_4to16_behavioral(input [3:0]a,output reg [15:0]d);

always @(*)begin

	d=16'b1 << a;

end
endmodule

module decoder_4to16_top (input [3:0]a,output [15:0]d_da,output [15:0]d_be);

 decoder_4to16_dataflow dec1(.a(a),.d(d_da));
  decoder_4to16_behavioral dec2(.a(a),.d(d_be));

  endmodule

combinational_ckt_using_dataflow_&_behavioral_modeling/4to16_decoder_data_beh.v/4to16_decoder_data_beh_tb.v
module decoder_4to16_data_beh_tb;
  
reg [3:0]a;
wire[15:0]d_da;
wire[15:0]d_be;

decoder_4to16_top dut(.a(a),.d_da(d_da),.d_be(d_be));

integer i;

initial begin

$dumpfile("decoder_4to16_data_beh.vcd");
$dumpvars(0,decoder_4to16_data_beh_tb);

$monitor("time=%0t | a=%b | d_da=%b,d_be=%b",$time,a,d_da,d_be);

for(i=0;i<16;i=i+1)begin

   a=i;#10;

end
$finish;
end
endmodule

combinational_ckt_using_dataflow_&_behavioral_modeling/4to16_decoder_data_beh.v/decoder_4to16_data_beh.vcd
$date
	Mon Mar 30 14:12:17 2026
$end
$version
	Icarus Verilog
$end
$timescale
	1s
$end
$scope module decoder_4to16_data_beh_tb $end
$var wire 16 ! d_da [15:0] $end
$var wire 16 " d_be [15:0] $end
$var reg 4 # a [3:0] $end
$var integer 32 $ i [31:0] $end
$scope module dut $end
$var wire 4 % a [3:0] $end
$var wire 16 & d_da [15:0] $end
$var wire 16 ' d_be [15:0] $end
$scope module dec1 $end
$var wire 4 ( a [3:0] $end
$var wire 16 ) d [15:0] $end
$upscope $end
$scope module dec2 $end
$var wire 4 * a [3:0] $end
$var reg 16 + d [15:0] $end
$upscope $end
$upscope $end
$upscope $end
$enddefinitions $end
$comment Show the parameter values. $end
$dumpall
$end
#0
$dumpvars
b1 +
b0 *
b1 )
b0 (
b1 '
b1 &
b0 %
b0 $
b0 #
b1 "
b1 !
$end
#10
b10 !
b10 &
b10 )
b10 "
b10 '
b10 +
b1 #
b1 %
b1 (
b1 *
b1 $
#20
b100 !
b100 &
b100 )
b100 "
b100 '
b100 +
b10 #
b10 %
b10 (
b10 *
b10 $
#30
b1000 !
b1000 &
b1000 )
b1000 "
b1000 '
b1000 +
b11 #
b11 %
b11 (
b11 *
b11 $
#40
b10000 !
b10000 &
b10000 )
b10000 "
b10000 '
b10000 +
b100 #
b100 %
b100 (
b100 *
b100 $
#50
b100000 !
b100000 &
b100000 )
b100000 "
b100000 '
b100000 +
b101 #
b101 %
b101 (
b101 *
b101 $
#60
b1000000 !
b1000000 &
b1000000 )
b1000000 "
b1000000 '
b1000000 +
b110 #
b110 %
b110 (
b110 *
b110 $
#70
b10000000 !
b10000000 &
b10000000 )
b10000000 "
b10000000 '
b10000000 +
b111 #
b111 %
b111 (
b111 *
b111 $
#80
b100000000 !
b100000000 &
b100000000 )
b100000000 "
b100000000 '
b100000000 +
b1000 #
b1000 %
b1000 (
b1000 *
b1000 $
#90
b1000000000 !
b1000000000 &
b1000000000 )
b1000000000 "
b1000000000 '
b1000000000 +
b1001 #
b1001 %
b1001 (
b1001 *
b1001 $
#100
b10000000000 !
b10000000000 &
b10000000000 )
b10000000000 "
b10000000000 '
b10000000000 +
b1010 #
b1010 %
b1010 (
b1010 *
b1010 $
#110
b100000000000 !
b100000000000 &
b100000000000 )
b100000000000 "
b100000000000 '
b100000000000 +
b1011 #
b1011 %
b1011 (
b1011 *
b1011 $
#120
b1000000000000 !
b1000000000000 &
b1000000000000 )
b1000000000000 "
b1000000000000 '
b1000000000000 +
b1100 #
b1100 %
b1100 (
b1100 *
b1100 $
#130
b10000000000000 !
b10000000000000 &
b10000000000000 )
b10000000000000 "
b10000000000000 '
b10000000000000 +
b1101 #
b1101 %
b1101 (
b1101 *
b1101 $
#140
b100000000000000 !
b100000000000000 &
b100000000000000 )
b100000000000000 "
b100000000000000 '
b100000000000000 +
b1110 #
b1110 %
b1110 (
b1110 *
b1110 $
#150
b1000000000000000 !
b1000000000000000 &
b1000000000000000 )
b1000000000000000 "
b1000000000000000 '
b1000000000000000 +
b1111 #
b1111 %
b1111 (
b1111 *
b1111 $
#160
b10000 $
