combinational_ckt_using_dataflow_&_behavioral_modeling/cla_adder_4bit_data_beh.v/cla_adder_4bit_data_beh.v
module cla_adder_4bit_dataflow(input [3:0]a,b,input cin,output [3:0]sum,output carry);

wire c1,c2,c3;
wire [3:0]g,p;

assign g =a & b;
assign p =a ^ b;

assign c1=g[0] | (p[0] & cin);
assign c2=g[1] | (p[1] & c1);
assign c3=g[2] | (p[2] & c2);
assign carry=g[3] | (p[3] & c3);

assign sum[0]=p[0]^cin;
assign sum[1]=p[1]^c1;
assign sum[2]=p[2]^c2;
assign sum[3]=p[3]^c3;

endmodule

module cla_adder_4bit_behavioral(input [3:0]a,b,input cin,output reg [3:0]sum,output reg carry);

reg c1,c2,c3;
reg [3:0]g,p;

always @(*)begin

 g =a & b;
 p = a ^ b;

 c1=g[0] | (p[0] & cin);
 c2=g[1] | (p[1] & c1);
 c3=g[2] | (p[2] & c2);
 carry=g[3] | (p[3] & c3);

 sum[0]=p[0]^cin;
 sum[1]=p[1]^c1;
 sum[2]=p[2]^c2;
 sum[3]=p[3]^c3;

end
endmodule

module cla_adder_4bit_top (input [3:0]a,b,input cin,output [3:0]sum_da,output carry_da,output [3:0]sum_be,output carry_be);

cla_adder_4bit_dataflow ad1(.a(a),.b(b),.cin(cin),.sum(sum_da),.carry(carry_da));
cla_adder_4bit_behavioral ad2(.a(a),.b(b),.cin(cin),.sum(sum_be),.carry(carry_be));

endmodule

combinational_ckt_using_dataflow_&_behavioral_modeling/cla_adder_4bit_data_beh.v/cla_adder_4bit_data_beh_tb.v
module cla_adder_4bit_data_beh_tb;

reg [3:0]a,b;
reg cin;
wire [3:0]sum_da;
wire carry_da;
wire [3:0]sum_be;
wire carry_be;

cla_adder_4bit_top dut(.a(a),.b(b),.cin(cin),.sum_da(sum_da),.carry_da(carry_da),.sum_be(sum_be),.carry_be(carry_be));

integer i;

initial begin

$dumpfile("cla_adder_4bit_data_beh.vcd");
$dumpvars(0,cla_adder_4bit_data_beh_tb);

$monitor("time=%0t | a=%b,b=%b,cin=%b | sum_da=%b,carry_da=%b,sum_be=%b,carry_be=%b",$time,a,b,cin,sum_da,carry_da,sum_be,carry_be);

for(i=0;i<32;i=i+1)begin

{a,b,cin}=i;#10;
end
end

endmodule

combinational_ckt_using_dataflow_&_behavioral_modeling/cla_adder_4bit_data_beh.v/cla_adder_4bit_data_beh.vcd
$date
	Mon Mar 30 10:50:35 2026
$end
$version
	Icarus Verilog
$end
$timescale
	1s
$end
$scope module cla_adder_4bit_data_beh_tb $end
$var wire 4 ! sum_da [3:0] $end
$var wire 4 " sum_be [3:0] $end
$var wire 1 # carry_da $end
$var wire 1 $ carry_be $end
$var reg 4 % a [3:0] $end
$var reg 4 & b [3:0] $end
$var reg 1 ' cin $end
$var integer 32 ( i [31:0] $end
$scope module dut $end
$var wire 4 ) a [3:0] $end
$var wire 4 * b [3:0] $end
$var wire 1 ' cin $end
$var wire 4 + sum_da [3:0] $end
$var wire 4 , sum_be [3:0] $end
$var wire 1 # carry_da $end
$var wire 1 $ carry_be $end
$scope module ad1 $end
$var wire 4 - a [3:0] $end
$var wire 4 . b [3:0] $end
$var wire 1 / c1 $end
$var wire 1 0 c2 $end
$var wire 1 1 c3 $end
$var wire 1 # carry $end
$var wire 1 ' cin $end
$var wire 4 2 g [3:0] $end
$var wire 4 3 p [3:0] $end
$var wire 4 4 sum [3:0] $end
$upscope $end
$scope module ad2 $end
$var wire 4 5 a [3:0] $end
$var wire 4 6 b [3:0] $end
$var wire 1 ' cin $end
$var reg 1 7 c1 $end
$var reg 1 8 c2 $end
$var reg 1 9 c3 $end
$var reg 1 $ carry $end
$var reg 4 : g [3:0] $end
$var reg 4 ; p [3:0] $end
$var reg 4 < sum [3:0] $end
$upscope $end
$upscope $end
$upscope $end
$enddefinitions $end
$comment Show the parameter values. $end
$dumpall
$end
#0
$dumpvars
b0 <
b0 ;
b0 :
09
08
07
b0 6
b0 5
b0 4
b0 3
b0 2
01
00
0/
b0 .
b0 -
b0 ,
b0 +
b0 *
b0 )
b0 (
0'
b0 &
b0 %
0$
0#
b0 "
b0 !
$end
#10
b1 !
b1 +
b1 4
b1 "
b1 ,
b1 <
1'
b1 (
#20
b1 3
b1 !
b1 +
b1 4
b1 ;
b1 &
b1 *
b1 .
b1 6
0'
b10 (
#30
1/
b10 !
b10 +
b10 4
b10 "
b10 ,
b10 <
17
1'
b11 (
#40
0/
b10 3
b10 !
b10 +
b10 4
07
b10 ;
b10 &
b10 *
b10 .
b10 6
0'
b100 (
#50
b11 !
b11 +
b11 4
b11 "
b11 ,
b11 <
1'
b101 (
#60
b11 3
b11 !
b11 +
b11 4
b11 ;
b11 &
b11 *
b11 .
b11 6
0'
b110 (
#70
10
1/
b100 !
b100 +
b100 4
b100 "
b100 ,
b100 <
18
17
1'
b111 (
#80
01
00
0/
b100 3
b100 !
b100 +
b100 4
08
07
b100 ;
b100 &
b100 *
b100 .
b100 6
0'
b1000 (
#90
b101 !
b101 +
b101 4
b101 "
b101 ,
b101 <
1'
b1001 (
#100
b101 3
b101 !
b101 +
b101 4
b101 ;
b101 &
b101 *
b101 .
b101 6
0'
b1010 (
#110
1/
b110 !
b110 +
b110 4
b110 "
b110 ,
b110 <
17
1'
b1011 (
#120
0/
b110 3
b110 !
b110 +
b110 4
07
b110 ;
b110 &
b110 *
b110 .
b110 6
0'
b1100 (
#130
b111 !
b111 +
b111 4
b111 "
b111 ,
b111 <
1'
b1101 (
#140
b111 3
b111 !
b111 +
b111 4
b111 ;
b111 &
b111 *
b111 .
b111 6
0'
b1110 (
#150
11
10
1/
b1000 !
b1000 +
b1000 4
b1000 "
b1000 ,
b1000 <
19
18
17
1'
b1111 (
#160
01
0#
00
0/
b1000 3
b1000 !
b1000 +
b1000 4
09
08
07
b1000 ;
b1000 &
b1000 *
b1000 .
b1000 6
0'
b10000 (
#170
b1001 !
b1001 +
b1001 4
b1001 "
b1001 ,
b1001 <
1'
b10001 (
#180
b1001 3
b1001 !
b1001 +
b1001 4
b1001 ;
b1001 &
b1001 *
b1001 .
b1001 6
0'
b10010 (
#190
1/
b1010 !
b1010 +
b1010 4
b1010 "
b1010 ,
b1010 <
17
1'
b10011 (
#200
0/
b1010 3
b1010 !
b1010 +
b1010 4
07
b1010 ;
b1010 &
b1010 *
b1010 .
b1010 6
0'
b10100 (
#210
b1011 !
b1011 +
b1011 4
b1011 "
b1011 ,
b1011 <
1'
b10101 (
#220
b1011 3
b1011 !
b1011 +
b1011 4
b1011 ;
b1011 &
b1011 *
b1011 .
b1011 6
0'
b10110 (
#230
10
1/
b1100 !
b1100 +
b1100 4
b1100 "
b1100 ,
b1100 <
18
17
1'
b10111 (
#240
0#
01
00
0/
b1100 3
b1100 !
b1100 +
b1100 4
08
07
b1100 ;
b1100 &
b1100 *
b1100 .
b1100 6
0'
b11000 (
#250
b1101 !
b1101 +
b1101 4
b1101 "
b1101 ,
b1101 <
1'
b11001 (
#260
b1101 3
b1101 !
b1101 +
b1101 4
b1101 ;
b1101 &
b1101 *
b1101 .
b1101 6
0'
b11010 (
#270
1/
b1110 !
b1110 +
b1110 4
b1110 "
b1110 ,
b1110 <
17
1'
b11011 (
#280
0/
b1110 3
b1110 !
b1110 +
b1110 4
07
b1110 ;
b1110 &
b1110 *
b1110 .
b1110 6
0'
b11100 (
#290
b1111 !
b1111 +
b1111 4
b1111 "
b1111 ,
b1111 <
1'
b11101 (
#300
b1111 3
b1111 !
b1111 +
b1111 4
b1111 ;
b1111 &
b1111 *
b1111 .
b1111 6
0'
b11110 (
#310
1#
11
10
1/
b0 !
b0 +
b0 4
b0 "
b0 ,
b0 <
1$
19
18
17
1'
b11111 (
#320
b100000 (
