combinational ckt using gate modeling/encoder_8to3.v/encoder_8to3.v
module encoder_8to3(input d0,d1,d2,d3,d4,d5,d6,d7,output a,b,c);
 
or o1(a,d3,d2,d1,d0);
or o2(b,d5,d4,d1,d0);
or o3(c,d6,d4,d2,d0);

endmodule

combinational circuits using gate modeling/encoder_8to3.v/encoder_8to3_tb.v
module encoder_8to3_tb;
reg d0,d1,d2,d3,d4,d5,d6,d7;
wire a,b,c;

encoder_8to3 dut(.d0(d0),.d1(d1),.d2(d2),.d3(d3),.d4(d4),.d5(d5),.d6(d6),.d7(d7),.a(a),.b(b),.c(c));

integer i;
initial begin

$dumpfile("encoder_8to3.vcd");
$dumpvars(0,encoder_8to3_tb);
  
$monitor("time=%0t | d0=%b,d1=%b,d2=%b,d3=%b,d4=%b,d5=%b,d6=%b,d7=%b | a=%b,b=%b,c=%b",$time,d0,d1,d2,d3,d4,d5,d6,d7,a,b,c);


for(i=0;i<8;i=i+1) begin
	{d0,d1,d2,d3,d4,d5,d6,d7}= 8'b00000001 << i;
#10;
end
$finish;
end
endmodule

combinational circuits using gate modeling/encoder_8to3.v/encoder_8to3.vcd
$date
	Fri Mar 27 11:48:21 2026
$end
$version
	Icarus Verilog
$end
$timescale
	1s
$end
$scope module encoder_8to3_tb $end
$var wire 1 ! c $end
$var wire 1 " b $end
$var wire 1 # a $end
$var reg 1 $ d0 $end
$var reg 1 % d1 $end
$var reg 1 & d2 $end
$var reg 1 ' d3 $end
$var reg 1 ( d4 $end
$var reg 1 ) d5 $end
$var reg 1 * d6 $end
$var reg 1 + d7 $end
$var integer 32 , i [31:0] $end
$scope module dut $end
$var wire 1 # a $end
$var wire 1 " b $end
$var wire 1 ! c $end
$var wire 1 $ d0 $end
$var wire 1 % d1 $end
$var wire 1 & d2 $end
$var wire 1 ' d3 $end
$var wire 1 ( d4 $end
$var wire 1 ) d5 $end
$var wire 1 * d6 $end
$var wire 1 + d7 $end
$upscope $end
$upscope $end
$enddefinitions $end
$comment Show the parameter values. $end
$dumpall
$end
#0
$dumpvars
b0 ,
1+
0*
0)
0(
0'
0&
0%
0$
0#
0"
0!
$end
#10
1!
1*
0+
b1 ,
#20
1"
0!
1)
0*
b10 ,
#30
1!
1(
0)
b11 ,
#40
1#
0"
0!
1'
0(
b100 ,
#50
1!
1&
0'
b101 ,
#60
1"
0!
1%
0&
b110 ,
#70
1!
1$
0%
b111 ,
#80
b1000 ,
