combinational_ckt_using_dataflow_&_behavioral_modeling/rca_4bit_data_beh.v/rca_4bit_data_beh.v
module rca_4bit_dataflow(input [3:0]a,b,input cin,output [3:0]sum,output carry);

wire w1,w2,w3;

assign sum[0]=a[0]^b[0]^cin;
assign w1=((a[0]&b[0])|(a[0]&cin)|(b[0]&cin));
 
assign sum[1]=a[1]^b[1]^w1;
assign w2=((a[1]&b[1])|(a[1]&w1)|(b[1]&w1));

assign sum[2]=a[2]^b[2]^w2;
assign w3=((a[2]&b[2])|(a[2]&w2)|(b[2]&w2));

assign sum[3]=a[3]^b[3]^w3;
assign carry=((a[3]&b[3])|(a[3]&w3)|(b[3]&w3));

endmodule

module rca_4bit_behavioral(input [3:0]a,b,input cin,output reg [3:0]sum,output reg carry);

integer i;
reg c;
always @(*)begin
	c=cin;
for(i=0;i<4;i=i+1)begin
    sum[i]=a[i]^b[i]^c;
    c=((a[i]&b[i])|(a[i]&c)|(b[i]&c));
end
   carry=c;
end
endmodule

module rca_4bit_top(input [3:0]a,b,input cin,output [3:0]sum_da,output carry_da,output [3:0]sum_be,output carry_be);

rca_4bit_dataflow rc1(.a(a),.b(b),.cin(cin),.sum(sum_da),.carry(carry_da));
rca_4bit_behavioral rc2(.a(a),.b(b),.cin(cin),.sum(sum_be),.carry(carry_be));

endmodule

combinational_ckt_using_dataflow_&_behavioral_modeling/rca_4bit_data_beh.v/rca_4bit_data_beh_tb.v
module rca_4bit_data_beh_tb;

reg [3:0]a,b;
reg cin;
wire [3:0]sum_da;
wire carry_da;
wire[3:0]sum_be;
wire carry_be;

rca_4bit_top dut(.a(a),.b(b),.cin(cin),.sum_da(sum_da),.carry_da(carry_da),.sum_be(sum_be),.carry_be(carry_be));

integer i;
initial begin

	$dumpfile("rca_4bit_data_beh.vcd");
	$dumpvars(0,rca_4bit_data_beh_tb);

	$monitor("time=%0t | a=%b,b=%b,cin=%b | sum_da=%b,carry_da=%b,sum_be=%b,carry_be=%b",$time,a,b,cin,sum_da,carry_da,sum_be,carry_be);

for(i=0;i<16;i=i+1)
begin
	{a,b,cin}=i;#10;

end
$finish;
end
endmodule

combinational_ckt_using_dataflow_&_behavioral_modeling/rca_4bit_data_beh.v/rca_4bit_data_beh.vcd
$date
	Sun Mar 29 13:49:12 2026
$end
$version
	Icarus Verilog
$end
$timescale
	1s
$end
$scope module rca_4bit_data_beh_tb $end
$var wire 4 ! sum_da [3:0] $end
$var wire 4 " sum_be [3:0] $end
$var wire 1 # carry_da $end
$var wire 1 $ carry_be $end
$var reg 4 % a [3:0] $end
$var reg 4 & b [3:0] $end
$var reg 1 ' cin $end
$var integer 32 ( i [31:0] $end
$scope module dut $end
$var wire 4 ) a [3:0] $end
$var wire 4 * b [3:0] $end
$var wire 1 ' cin $end
$var wire 4 + sum_da [3:0] $end
$var wire 4 , sum_be [3:0] $end
$var wire 1 # carry_da $end
$var wire 1 $ carry_be $end
$scope module rc1 $end
$var wire 4 - a [3:0] $end
$var wire 4 . b [3:0] $end
$var wire 1 # carry $end
$var wire 1 ' cin $end
$var wire 1 / w1 $end
$var wire 1 0 w2 $end
$var wire 1 1 w3 $end
$var wire 4 2 sum [3:0] $end
$upscope $end
$scope module rc2 $end
$var wire 4 3 a [3:0] $end
$var wire 4 4 b [3:0] $end
$var wire 1 ' cin $end
$var reg 1 5 c $end
$var reg 1 $ carry $end
$var reg 4 6 sum [3:0] $end
$var integer 32 7 i [31:0] $end
$upscope $end
$upscope $end
$upscope $end
$enddefinitions $end
$comment Show the parameter values. $end
$dumpall
$end
#0
$dumpvars
b100 7
b0 6
05
b0 4
b0 3
b0 2
01
00
0/
b0 .
b0 -
b0 ,
b0 +
b0 *
b0 )
b0 (
0'
b0 &
b0 %
0$
0#
b0 "
b0 !
$end
#10
b1 !
b1 +
b1 2
b1 "
b1 ,
b1 6
b100 7
05
1'
b1 (
#20
b1 !
b1 +
b1 2
b100 7
b1 &
b1 *
b1 .
b1 4
0'
b10 (
#30
1/
b10 !
b10 +
b10 2
b10 "
b10 ,
b10 6
b100 7
05
1'
b11 (
#40
0/
b10 !
b10 +
b10 2
b100 7
b10 &
b10 *
b10 .
b10 4
0'
b100 (
#50
b11 !
b11 +
b11 2
b11 "
b11 ,
b11 6
b100 7
05
1'
b101 (
#60
b11 !
b11 +
b11 2
b100 7
b11 &
b11 *
b11 .
b11 4
0'
b110 (
#70
10
1/
b100 !
b100 +
b100 2
b100 "
b100 ,
b100 6
b100 7
05
1'
b111 (
#80
00
01
0/
b100 !
b100 +
b100 2
b100 7
b100 &
b100 *
b100 .
b100 4
0'
b1000 (
#90
b101 !
b101 +
b101 2
b101 "
b101 ,
b101 6
b100 7
05
1'
b1001 (
#100
b101 !
b101 +
b101 2
b100 7
b101 &
b101 *
b101 .
b101 4
0'
b1010 (
#110
1/
b110 !
b110 +
b110 2
b110 "
b110 ,
b110 6
b100 7
05
1'
b1011 (
#120
0/
b110 !
b110 +
b110 2
b100 7
b110 &
b110 *
b110 .
b110 4
0'
b1100 (
#130
b111 !
b111 +
b111 2
b111 "
b111 ,
b111 6
b100 7
05
1'
b1101 (
#140
b111 !
b111 +
b111 2
b100 7
b111 &
b111 *
b111 .
b111 4
0'
b1110 (
#150
11
10
1/
b1000 !
b1000 +
b1000 2
b1000 "
b1000 ,
b1000 6
b100 7
05
1'
b1111 (
#160
b10000 (
