combinational_ckt_using_dataflow_&_behavioral_modeling/full_subtractor_data_beh.v/full_subtractor_data_beh.v
module full_subtractor_dataflow (input a,b,bin,output diff,borrow);


assign diff=a^b^bin;
assign borrow=(~a&b)|(~a&bin)|(b&bin);

endmodule

module full_subtractor_behavioral (input a,b,bin,output reg diff,borrow);

always @(*)begin

  diff=a^b^bin;
  borrow=(~a&b)|(~a&bin)|(b&bin);

end
endmodule

module full_subtractor_top(input a,b,bin,output diff_da,borrow_da,output diff_be,borrow_be);

  full_subtractor_dataflow fs1(.a(a),.b(b),.bin(bin),.diff(diff_da),.borrow(borrow_da));

  full_subtractor_behavioral fs2 (.a(a),.b(b),.bin(bin),.diff(diff_be),.borrow(borrow_be));

   endmodule

combinational_ckt_using_dataflow_&_behavioral_modeling/full_subtractor_data_beh.v/full_subtractor_data_beh_tb.v
module full_subtractor_data_beh_tb;

reg a,b,bin;
wire diff_da,borrow_da;
wire diff_be,borrow_be;
full_subtractor_top dut(.a(a),.b(b),.bin(bin),.diff_da(diff_da),.borrow_da(borrow_da),.diff_be(diff_be),.borrow_be(borrow_be));

initial begin

$dumpfile("full_subtractor_data_beh.vcd");
$dumpvars(0,full_subtractor_data_beh_tb);

$monitor("time=%0t | a=%b,b=%b,bin=%b| diff_da=%b,borrow_da=%b,diff_be=%b,borrow_be=%b",$time,a,b,bin,diff_da,borrow_da,diff_be,borrow_be);

a=0;b=0;bin=0;#10;
a=0;b=0;bin=1;#10;
a=0;b=1;bin=0;#10;
a=0;b=1;bin=1;#10;
a=1;b=0;bin=0;#10;
a=1;b=0;bin=1;#10;
a=1;b=1;bin=0;#10;
a=1;b=1;bin=1;#10;

$finish;
end
endmodule

combinational_ckt_using_dataflow_&_behavioral_modeling/full_subtractor_data_beh.v/full_subtractor_data_beh.vcd
$date
	Sat Mar 28 10:28:28 2026
$end
$version
	Icarus Verilog
$end
$timescale
	1s
$end
$scope module full_subtractor_data_beh_tb $end
$var wire 1 ! diff_da $end
$var wire 1 " diff_be $end
$var wire 1 # borrow_da $end
$var wire 1 $ borrow_be $end
$var reg 1 % a $end
$var reg 1 & b $end
$var reg 1 ' bin $end
$scope module dut $end
$var wire 1 % a $end
$var wire 1 & b $end
$var wire 1 ' bin $end
$var wire 1 ! diff_da $end
$var wire 1 " diff_be $end
$var wire 1 # borrow_da $end
$var wire 1 $ borrow_be $end
$scope module fs1 $end
$var wire 1 % a $end
$var wire 1 & b $end
$var wire 1 ' bin $end
$var wire 1 # borrow $end
$var wire 1 ! diff $end
$upscope $end
$scope module fs2 $end
$var wire 1 % a $end
$var wire 1 & b $end
$var wire 1 ' bin $end
$var reg 1 $ borrow $end
$var reg 1 " diff $end
$upscope $end
$upscope $end
$upscope $end
$enddefinitions $end
$comment Show the parameter values. $end
$dumpall
$end
#0
$dumpvars
0'
0&
0%
0$
0#
0"
0!
$end
#10
1#
1!
1$
1"
1'
#20
0'
1&
#30
0!
0"
1'
#40
0#
1!
0$
1"
0'
0&
1%
#50
0!
0"
1'
#60
0'
1&
#70
1#
1!
1$
1"
1'
