combinational_ckt_using_dataflow_&_behavioral_modeling/encoder_4to16_data_beh.v/encoder_4to16_data_beh.v
module encoder_16to4_dataflow(input [15:0]d,output [3:0]a);

assign a=(d==(16'b1<<0)) ? 4'd0:
(d==(16'b1<<1)) ? 4'd1:
(d==(16'b1<<2)) ? 4'd2:
(d==(16'b1<<3)) ? 4'd3:
(d==(16'b1<<4)) ? 4'd4:
(d==(16'b1<<5)) ? 4'd5:
(d==(16'b1<<6)) ? 4'd6:
(d==(16'b1<<7)) ? 4'd7:
(d==(16'b1<<8)) ? 4'd8:
(d==(16'b1<<9)) ? 4'd9:
(d==(16'b1<<10)) ? 4'd10:
(d==(16'b1<<11)) ? 4'd11:
(d==(16'b1<<12)) ? 4'd12:
(d==(16'b1<<13)) ? 4'd13:
(d==(16'b1<<14)) ? 4'd14:
(d==(16'b1<<15)) ? 4'd15:
4'd0;


endmodule

module encoder_16to4_behavioral(input [15:0]d,output reg [3:0]a);

integer i;
 
always @(*)begin
   
   a=4'd0;

for(i=0;i<16;i=i+1)begin
    if(d==16'b1 <<i)
    a=i[3:0];

end
end
endmodule

module encoder_16to4_top(input [15:0]d,output [3:0]a_da,output [3:0]a_be);

 encoder_16to4_dataflow en1(.d(d),.a(a_da));
 encoder_16to4_behavioral en2(.d(d),.a(a_be));

endmodule

combinational_ckt_using_dataflow_&_behavioral_modeling/encoder_4to16_data_beh.v/encoder_4to16_data_beh_tb.v
module encoder_16to4_data_beh_tb;
  
reg [15:0]d;
wire[3:0]a_da;
wire[3:0]a_be;

encoder_16to4_top dut(.d(d),.a_da(a_da),.a_be(a_be));

integer i;

initial begin

$dumpfile("encoder_16to4_data_beh.vcd");
$dumpvars(0,encoder_16to4_data_beh_tb);

$monitor("time=%0t | d=%b | a_da=%b,a_be=%b",$time,d,a_da,a_be);

for(i=0;i<16;i=i+1)begin

	d=16'b1<<i;
   #10;

end
$finish;
end
endmodule

combinational_ckt_using_dataflow_&_behavioral_modeling/encoder_4to16_data_beh.v/encoder_16to4_data_beh.vcd
$date
	Tue Mar 31 07:35:09 2026
$end
$version
	Icarus Verilog
$end
$timescale
	1s
$end
$scope module encoder_16to4_data_beh_tb $end
$var wire 4 ! a_da [3:0] $end
$var wire 4 " a_be [3:0] $end
$var reg 16 # d [15:0] $end
$var integer 32 $ i [31:0] $end
$scope module dut $end
$var wire 16 % d [15:0] $end
$var wire 4 & a_da [3:0] $end
$var wire 4 ' a_be [3:0] $end
$scope module en1 $end
$var wire 16 ( d [15:0] $end
$var wire 4 ) a [3:0] $end
$upscope $end
$scope module en2 $end
$var wire 16 * d [15:0] $end
$var reg 4 + a [3:0] $end
$var integer 32 , i [31:0] $end
$upscope $end
$upscope $end
$upscope $end
$enddefinitions $end
$comment Show the parameter values. $end
$dumpall
$end
#0
$dumpvars
b10000 ,
b0 +
b1 *
b0 )
b1 (
b0 '
b0 &
b1 %
b0 $
b1 #
b0 "
b0 !
$end
#10
b1 !
b1 &
b1 )
b1 "
b1 '
b1 +
b10000 ,
b10 #
b10 %
b10 (
b10 *
b1 $
#20
b10 !
b10 &
b10 )
b10000 ,
b10 "
b10 '
b10 +
b100 #
b100 %
b100 (
b100 *
b10 $
#30
b11 !
b11 &
b11 )
b10000 ,
b11 "
b11 '
b11 +
b1000 #
b1000 %
b1000 (
b1000 *
b11 $
#40
b100 !
b100 &
b100 )
b10000 ,
b100 "
b100 '
b100 +
b10000 #
b10000 %
b10000 (
b10000 *
b100 $
#50
b101 !
b101 &
b101 )
b10000 ,
b101 "
b101 '
b101 +
b100000 #
b100000 %
b100000 (
b100000 *
b101 $
#60
b110 !
b110 &
b110 )
b10000 ,
b110 "
b110 '
b110 +
b1000000 #
b1000000 %
b1000000 (
b1000000 *
b110 $
#70
b111 !
b111 &
b111 )
b10000 ,
b111 "
b111 '
b111 +
b10000000 #
b10000000 %
b10000000 (
b10000000 *
b111 $
#80
b1000 !
b1000 &
b1000 )
b10000 ,
b1000 "
b1000 '
b1000 +
b100000000 #
b100000000 %
b100000000 (
b100000000 *
b1000 $
#90
b1001 !
b1001 &
b1001 )
b10000 ,
b1001 "
b1001 '
b1001 +
b1000000000 #
b1000000000 %
b1000000000 (
b1000000000 *
b1001 $
#100
b1010 !
b1010 &
b1010 )
b10000 ,
b1010 "
b1010 '
b1010 +
b10000000000 #
b10000000000 %
b10000000000 (
b10000000000 *
b1010 $
#110
b1011 !
b1011 &
b1011 )
b10000 ,
b1011 "
b1011 '
b1011 +
b100000000000 #
b100000000000 %
b100000000000 (
b100000000000 *
b1011 $
#120
b1100 !
b1100 &
b1100 )
b10000 ,
b1100 "
b1100 '
b1100 +
b1000000000000 #
b1000000000000 %
b1000000000000 (
b1000000000000 *
b1100 $
#130
b1101 !
b1101 &
b1101 )
b10000 ,
b1101 "
b1101 '
b1101 +
b10000000000000 #
b10000000000000 %
b10000000000000 (
b10000000000000 *
b1101 $
#140
b1110 !
b1110 &
b1110 )
b10000 ,
b1110 "
b1110 '
b1110 +
b100000000000000 #
b100000000000000 %
b100000000000000 (
b100000000000000 *
b1110 $
#150
b1111 !
b1111 &
b1111 )
b10000 ,
b1111 "
b1111 '
b1111 +
b1000000000000000 #
b1000000000000000 %
b1000000000000000 (
b1000000000000000 *
b1111 $
#160
b10000 $
